LICENSE
README.md
setup.py
lnurl/__init__.py
lnurl/lnurlpay.py
lnurl/lnurlwithdraw.py
micropython_lnurl.egg-info/PKG-INFO
micropython_lnurl.egg-info/SOURCES.txt
micropython_lnurl.egg-info/dependency_links.txt
micropython_lnurl.egg-info/requires.txt
micropython_lnurl.egg-info/top_level.txt